MANIFEST.in
README.rst
setup.py
thechristmaspig/__init__.py
thechristmaspig/application.wsgi
thechristmaspig/manage.py
thechristmaspig/recipe.py
thechristmaspig/settings.py
thechristmaspig/urls.py
thechristmaspig/wsgi.py
thechristmaspig.egg-info/PKG-INFO
thechristmaspig.egg-info/SOURCES.txt
thechristmaspig.egg-info/dependency_links.txt
thechristmaspig.egg-info/entry_points.txt
thechristmaspig.egg-info/not-zip-safe
thechristmaspig.egg-info/requires.txt
thechristmaspig.egg-info/top_level.txt