Metadata-Version: 1.0
Name: thechristmaspig
Version: 0.9.5
Summary: Buildout recipe for Django. Sets up controls scripts and wsgi file.
Home-page: http://github.com/prestontimmons/thechristmaspig
Author: Preston Timmons
Author-email: prestontimmons@gmail.com
License: BSD
Platform: UNKNOWN
Classifier: Framework :: Buildout
Classifier: Framework :: Django
Classifier: Topic :: Software Development :: Build Tools
Classifier: License :: OSI Approved :: BSD License
